langgraph_swarm/__init__.py
langgraph_swarm/handoff.py
langgraph_swarm/py.typed
langgraph_swarm/swarm.py
langgraph_swarm_brim-0.0.14.dist-info/METADATA
langgraph_swarm_brim-0.0.14.dist-info/WHEEL
langgraph_swarm_brim-0.0.14.dist-info/entry_points.txt
langgraph_swarm_brim-0.0.14.dist-info/licenses/LICENSE
langgraph_swarm_brim-0.0.14.dist-info/RECORD
