Metadata-Version: 2.4
Name: langgraph-swarm-brim
Version: 0.0.14
Summary: An implementation of a multi-agent swarm using LangGraph
Author-Email: Vadym Barda <19161700+vbarda@users.noreply.github.com >
License-Expression: MIT
License-File: LICENSE
Requires-Python: >=3.10
Requires-Dist: langgraph>=0.6.0
Requires-Dist: langchain-core>=0.3.40
